ultra/__init__.py
ultra/analysis.py
ultra/fitting.py
ultra/main.py
ultra/utils.py
ultra/visualization.py
ultrafast_fit-1.9.8.dist-info/METADATA
ultrafast_fit-1.9.8.dist-info/WHEEL
ultrafast_fit-1.9.8.dist-info/entry_points.txt
ultrafast_fit-1.9.8.dist-info/top_level.txt
ultrafast_fit-1.9.8.dist-info/RECORD
