Metadata-Version: 2.4
Name: ultrafast-fit
Version: 1.9.8
Summary: Ultrafast spectroscopy fitting toolkit
Requires-Python: >=3.8
Requires-Dist: numpy
Requires-Dist: pandas
Requires-Dist: matplotlib
Requires-Dist: lmfit
Requires-Dist: scikit-learn
Requires-Dist: seaborn
Dynamic: requires-python
